[{"sum_tx":105701,"sum_pt":2114022,"count_block":16,"max_time":1528541749802,"ac_active_5min":339},{"sum_tx":47002,"sum_pt":940048,"count_block":9,"max_time":1528541751507,"ac_active_5min":334},{"sum_tx":47940,"sum_pt":958796,"count_block":8,"max_time":1528541755479,"ac_active_5min":327},{"sum_tx":63199,"sum_pt":1263989,"count_block":8,"max_time":1528541759540,"ac_active_5min":332},{"sum_tx":58244,"sum_pt":1164879,"count_block":13,"max_time":1528541761702,"ac_active_5min":341},{"sum_tx":57320,"sum_pt":1146399,"count_block":11,"max_time":1528541765792,"ac_active_5min":333},{"sum_tx":63662,"sum_pt":1273234,"count_block":11,"max_time":1528541753717,"ac_active_5min":333},{"sum_tx":47102,"sum_pt":942048,"count_block":11,"max_time":1528541757790,"ac_active_5min":330},{"sum_tx":48442,"sum_pt":968842,"count_block":10,"max_time":1528541763510,"ac_active_5min":333},{"sum_tx":31850,"sum_pt":636996,"count_block":10,"max_time":1528541767705,"ac_active_5min":332},{"sum_tx":75935,"sum_pt":1518692,"count_block":17,"max_time":1528541769779,"ac_active_5min":338},{"sum_tx":54074,"sum_pt":1081485,"count_block":10,"max_time":1528541771800,"ac_active_5min":336},{"sum_tx":99404,"sum_pt":1988071,"count_block":18,"max_time":1528541775803,"ac_active_5min":340},{"sum_tx":18815,"sum_pt":376296,"count_block":3,"max_time":1528541781737,"ac_active_5min":334},{"sum_tx":14752,"sum_pt":295038,"count_block":4,"max_time":1528541787666,"ac_active_5min":322},{"sum_tx":48804,"sum_pt":976082,"count_block":11,"max_time":1528541791721,"ac_active_5min":328},{"sum_tx":49713,"sum_pt":994261,"count_block":11,"max_time":1528541795237,"ac_active_5min":328},{"sum_tx":68350,"sum_pt":1366991,"count_block":14,"max_time":1528541773562,"ac_active_5min":334},{"sum_tx":63080,"sum_pt":1261597,"count_block":10,"max_time":1528541777554,"ac_active_5min":340},{"sum_tx":64980,"sum_pt":1299606,"count_block":11,"max_time":1528541779677,"ac_active_5min":341},{"sum_tx":51304,"sum_pt":1026085,"count_block":10,"max_time":1528541783405,"ac_active_5min":334},{"sum_tx":62334,"sum_pt":1246689,"count_block":12,"max_time":1528541785793,"ac_active_5min":333},{"sum_tx":65638,"sum_pt":1312759,"count_block":15,"max_time":1528541789716,"ac_active_5min":330},{"sum_tx":81802,"sum_pt":1636039,"count_block":15,"max_time":1528541793704,"ac_active_5min":328},{"sum_tx":47846,"sum_pt":956912,"count_block":7,"max_time":1528541799394,"ac_active_5min":329},{"sum_tx":26050,"sum_pt":521003,"count_block":6,"max_time":1528541801583,"ac_active_5min":326},{"sum_tx":66718,"sum_pt":1334368,"count_block":13,"max_time":1528541805800,"ac_active_5min":333},{"sum_tx":63227,"sum_pt":1264533,"count_block":16,"max_time":1528541811543,"ac_active_5min":325},{"sum_tx":108455,"sum_pt":2169099,"count_block":18,"max_time":1528541815754,"ac_active_5min":336},{"sum_tx":91958,"sum_pt":1839156,"count_block":18,"max_time":1528541797636,"ac_active_5min":337},{"sum_tx":45142,"sum_pt":0,"count_block":12,"max_time":1528541803651,"ac_active_5min":328},{"sum_tx":49523,"sum_pt":990453,"count_block":8,"max_time":1528541807628,"ac_active_5min":327},{"sum_tx":37048,"sum_pt":740961,"count_block":7,"max_time":1528541808518,"ac_active_5min":318},{"sum_tx":66961,"sum_pt":1339226,"count_block":12,"max_time":1528541813415,"ac_active_5min":325},{"sum_tx":61333,"sum_pt":1226662,"count_block":11,"max_time":1528541817785,"ac_active_5min":333},{"sum_tx":64650,"sum_pt":1292992,"count_block":12,"max_time":1528541819782,"ac_active_5min":339},{"sum_tx":42935,"sum_pt":858695,"count_block":8,"max_time":1528541823439,"ac_active_5min":338},{"sum_tx":46808,"sum_pt":936156,"count_block":14,"max_time":1528541821763,"ac_active_5min":339},{"sum_tx":80511,"sum_pt":1610217,"count_block":17,"max_time":1528541825713,"ac_active_5min":344},{"sum_tx":61242,"sum_pt":1224839,"count_block":12,"max_time":1528541829671,"ac_active_5min":338},{"sum_tx":59642,"sum_pt":1192848,"count_block":12,"max_time":1528541831638,"ac_active_5min":340},{"sum_tx":35511,"sum_pt":710212,"count_block":7,"max_time":1528541835704,"ac_active_5min":325},{"sum_tx":34391,"sum_pt":0,"count_block":9,"max_time":1528541827521,"ac_active_5min":343},{"sum_tx":46554,"sum_pt":931074,"count_block":9,"max_time":1528541833771,"ac_active_5min":334},{"sum_tx":32116,"sum_pt":642310,"count_block":8,"max_time":1528541841697,"ac_active_5min":332},{"sum_tx":48612,"sum_pt":972245,"count_block":11,"max_time":1528541845787,"ac_active_5min":336},{"sum_tx":57847,"sum_pt":1156935,"count_block":10,"max_time":1528541849771,"ac_active_5min":338},{"sum_tx":27229,"sum_pt":0,"count_block":10,"max_time":1528541853772,"ac_active_5min":336},{"sum_tx":81925,"sum_pt":1638507,"count_block":12,"max_time":1528541857504,"ac_active_5min":330},{"sum_tx":48946,"sum_pt":978919,"count_block":10,"max_time":1528541861675,"ac_active_5min":337},{"sum_tx":60332,"sum_pt":1206647,"count_block":16,"max_time":1528541865685,"ac_active_5min":335},{"sum_tx":68366,"sum_pt":1367326,"count_block":11,"max_time":1528541837755,"ac_active_5min":325},{"sum_tx":59903,"sum_pt":1198057,"count_block":12,"max_time":1528541839378,"ac_active_5min":327},{"sum_tx":87179,"sum_pt":1743570,"count_block":17,"max_time":1528541843765,"ac_active_5min":338},{"sum_tx":81336,"sum_pt":1626714,"count_block":12,"max_time":1528541847657,"ac_active_5min":344},{"sum_tx":76564,"sum_pt":1531275,"count_block":13,"max_time":1528541851397,"ac_active_5min":341},{"sum_tx":44761,"sum_pt":895222,"count_block":10,"max_time":1528541855796,"ac_active_5min":336},{"sum_tx":46868,"sum_pt":937370,"count_block":9,"max_time":1528541858970,"ac_active_5min":333},{"sum_tx":35963,"sum_pt":719257,"count_block":8,"max_time":1528541863570,"ac_active_5min":332},{"sum_tx":39238,"sum_pt":784769,"count_block":12,"max_time":1528541873808,"ac_active_5min":339},{"sum_tx":36503,"sum_pt":730052,"count_block":8,"max_time":1528541877720,"ac_active_5min":326},{"sum_tx":51481,"sum_pt":1029629,"count_block":13,"max_time":1528541881554,"ac_active_5min":323},{"sum_tx":51844,"sum_pt":1036887,"count_block":13,"max_time":1528541885749,"ac_active_5min":327},{"sum_tx":24237,"sum_pt":484734,"count_block":8,"max_time":1528541889615,"ac_active_5min":324},{"sum_tx":23321,"sum_pt":466418,"count_block":7,"max_time":1528541893784,"ac_active_5min":325},{"sum_tx":63100,"sum_pt":1261999,"count_block":15,"max_time":1528541897509,"ac_active_5min":332},{"sum_tx":65586,"sum_pt":1311722,"count_block":12,"max_time":1528541899364,"ac_active_5min":331},{"sum_tx":76920,"sum_pt":1538396,"count_block":15,"max_time":1528541901738,"ac_active_5min":339},{"sum_tx":55583,"sum_pt":1111666,"count_block":12,"max_time":1528541905569,"ac_active_5min":333},{"sum_tx":58238,"sum_pt":1164763,"count_block":10,"max_time":1528541909298,"ac_active_5min":332},{"sum_tx":51803,"sum_pt":1036060,"count_block":9,"max_time":1528541911363,"ac_active_5min":329},{"sum_tx":51914,"sum_pt":1038274,"count_block":10,"max_time":1528541867395,"ac_active_5min":337},{"sum_tx":61161,"sum_pt":1223219,"count_block":14,"max_time":1528541869710,"ac_active_5min":344},{"sum_tx":51572,"sum_pt":1031432,"count_block":11,"max_time":1528541871763,"ac_active_5min":339},{"sum_tx":42011,"sum_pt":840227,"count_block":7,"max_time":1528541875802,"ac_active_5min":329},{"sum_tx":63125,"sum_pt":1262507,"count_block":10,"max_time":1528541879792,"ac_active_5min":323},{"sum_tx":75292,"sum_pt":1505845,"count_block":16,"max_time":1528541883805,"ac_active_5min":331},{"sum_tx":39866,"sum_pt":797322,"count_block":11,"max_time":1528541887477,"ac_active_5min":329},{"sum_tx":79004,"sum_pt":1580085,"count_block":14,"max_time":1528541891805,"ac_active_5min":327},{"sum_tx":50083,"sum_pt":1001662,"count_block":10,"max_time":1528541895696,"ac_active_5min":327},{"sum_tx":53539,"sum_pt":1070770,"count_block":10,"max_time":1528541903340,"ac_active_5min":332},{"sum_tx":55151,"sum_pt":1103022,"count_block":12,"max_time":1528541907793,"ac_active_5min":333},{"sum_tx":68772,"sum_pt":1375434,"count_block":14,"max_time":1528541913719,"ac_active_5min":333},{"sum_tx":59540,"sum_pt":1190795,"count_block":11,"max_time":1528541917807,"ac_active_5min":333},{"sum_tx":86731,"sum_pt":1734618,"count_block":11,"max_time":1528541923617,"ac_active_5min":343},{"sum_tx":39519,"sum_pt":790381,"count_block":8,"max_time":1528541927675,"ac_active_5min":339},{"sum_tx":68072,"sum_pt":1361436,"count_block":13,"max_time":1528541929753,"ac_active_5min":337},{"sum_tx":38025,"sum_pt":0,"count_block":11,"max_time":1528541931785,"ac_active_5min":338},{"sum_tx":71489,"sum_pt":1429781,"count_block":14,"max_time":1528541935652,"ac_active_5min":344},{"sum_tx":44813,"sum_pt":896263,"count_block":12,"max_time":1528541915751,"ac_active_5min":335},{"sum_tx":49590,"sum_pt":991794,"count_block":11,"max_time":1528541919804,"ac_active_5min":335},{"sum_tx":87903,"sum_pt":1758068,"count_block":16,"max_time":1528541921765,"ac_active_5min":341},{"sum_tx":73793,"sum_pt":1475855,"count_block":13,"max_time":1528541925793,"ac_active_5min":341},{"sum_tx":56490,"sum_pt":1129803,"count_block":10,"max_time":1528541933594,"ac_active_5min":337},{"sum_tx":31046,"sum_pt":620928,"count_block":8,"max_time":1528541937604,"ac_active_5min":343},{"sum_tx":71475,"sum_pt":1429498,"count_block":14,"max_time":1528541939297,"ac_active_5min":348},{"sum_tx":82045,"sum_pt":1640896,"count_block":15,"max_time":1528541941667,"ac_active_5min":350},{"sum_tx":37870,"sum_pt":757391,"count_block":7,"max_time":1528541947803,"ac_active_5min":341},{"sum_tx":52822,"sum_pt":1056435,"count_block":9,"max_time":1528541953799,"ac_active_5min":336},{"sum_tx":58344,"sum_pt":1166883,"count_block":11,"max_time":1528541955427,"ac_active_5min":337},{"sum_tx":54404,"sum_pt":1088077,"count_block":11,"max_time":1528541943455,"ac_active_5min":344},{"sum_tx":59161,"sum_pt":1183226,"count_block":13,"max_time":1528541945779,"ac_active_5min":345},{"sum_tx":18153,"sum_pt":363051,"count_block":3,"max_time":1528541949801,"ac_active_5min":336},{"sum_tx":71620,"sum_pt":1432402,"count_block":12,"max_time":1528541951662,"ac_active_5min":334},{"sum_tx":34345,"sum_pt":686890,"count_block":9,"max_time":1528541957770,"ac_active_5min":331},{"sum_tx":73424,"sum_pt":1468474,"count_block":11,"max_time":1528541959639,"ac_active_5min":330},{"sum_tx":52687,"sum_pt":1053742,"count_block":11,"max_time":1528541963705,"ac_active_5min":326},{"sum_tx":72155,"sum_pt":1443098,"count_block":13,"max_time":1528541969608,"ac_active_5min":331},{"sum_tx":72600,"sum_pt":1451995,"count_block":14,"max_time":1528541971757,"ac_active_5min":336},{"sum_tx":40221,"sum_pt":804418,"count_block":8,"max_time":1528541975768,"ac_active_5min":331},{"sum_tx":62911,"sum_pt":1258217,"count_block":10,"max_time":1528541961650,"ac_active_5min":325},{"sum_tx":27893,"sum_pt":557867,"count_block":8,"max_time":1528541964951,"ac_active_5min":321},{"sum_tx":87519,"sum_pt":1750381,"count_block":18,"max_time":1528541967749,"ac_active_5min":327},{"sum_tx":62024,"sum_pt":1240476,"count_block":13,"max_time":1528541973721,"ac_active_5min":333},{"sum_tx":26178,"sum_pt":523564,"count_block":10,"max_time":1528541979645,"ac_active_5min":330},{"sum_tx":65416,"sum_pt":1308313,"count_block":11,"max_time":1528541983815,"ac_active_5min":326},{"sum_tx":31234,"sum_pt":624685,"count_block":6,"max_time":1528541987781,"ac_active_5min":321},{"sum_tx":47698,"sum_pt":953954,"count_block":9,"max_time":1528541989645,"ac_active_5min":317},{"sum_tx":32706,"sum_pt":654113,"count_block":7,"max_time":1528541993549,"ac_active_5min":313},{"sum_tx":57300,"sum_pt":1145993,"count_block":8,"max_time":1528541995719,"ac_active_5min":309},{"sum_tx":55115,"sum_pt":1102302,"count_block":11,"max_time":1528541977504,"ac_active_5min":328},{"sum_tx":69728,"sum_pt":1394551,"count_block":13,"max_time":1528541981771,"ac_active_5min":327},{"sum_tx":40944,"sum_pt":0,"count_block":12,"max_time":1528541991762,"ac_active_5min":317},{"sum_tx":45534,"sum_pt":910679,"count_block":8,"max_time":1528541997748,"ac_active_5min":308},{"sum_tx":62840,"sum_pt":1256802,"count_block":10,"max_time":1528541999814,"ac_active_5min":304},{"sum_tx":24837,"sum_pt":496745,"count_block":7,"max_time":1528542001505,"ac_active_5min":296},{"sum_tx":82544,"sum_pt":1650877,"count_block":14,"max_time":1528542005733,"ac_active_5min":297},{"sum_tx":37050,"sum_pt":741007,"count_block":9,"max_time":1528541985696,"ac_active_5min":323},{"sum_tx":52580,"sum_pt":1051597,"count_block":10,"max_time":1528542003780,"ac_active_5min":296},{"sum_tx":74580,"sum_pt":1491598,"count_block":12,"max_time":1528542007698,"ac_active_5min":302},{"sum_tx":62225,"sum_pt":1244507,"count_block":9,"max_time":1528542015499,"ac_active_5min":313},{"sum_tx":28437,"sum_pt":568744,"count_block":7,"max_time":1528542021303,"ac_active_5min":319},{"sum_tx":72648,"sum_pt":1452952,"count_block":11,"max_time":1528542025694,"ac_active_5min":318},{"sum_tx":72128,"sum_pt":1442560,"count_block":14,"max_time":1528542009605,"ac_active_5min":312},{"sum_tx":60152,"sum_pt":1203041,"count_block":11,"max_time":1528542011625,"ac_active_5min":311},{"sum_tx":98539,"sum_pt":1970787,"count_block":17,"max_time":1528542017325,"ac_active_5min":319},{"sum_tx":74684,"sum_pt":1493680,"count_block":12,"max_time":1528542019628,"ac_active_5min":322},{"sum_tx":34755,"sum_pt":695100,"count_block":8,"max_time":1528542023394,"ac_active_5min":316},{"sum_tx":21007,"sum_pt":420130,"count_block":5,"max_time":1528542027184,"ac_active_5min":307},{"sum_tx":49118,"sum_pt":982354,"count_block":11,"max_time":1528542029423,"ac_active_5min":305},{"sum_tx":53521,"sum_pt":1070421,"count_block":11,"max_time":1528542031789,"ac_active_5min":302},{"sum_tx":61584,"sum_pt":1231682,"count_block":13,"max_time":1528542035753,"ac_active_5min":303},{"sum_tx":44562,"sum_pt":891242,"count_block":11,"max_time":1528542039444,"ac_active_5min":307},{"sum_tx":78208,"sum_pt":1564151,"count_block":13,"max_time":1528542041412,"ac_active_5min":307},{"sum_tx":77237,"sum_pt":1544738,"count_block":18,"max_time":1528542045806,"ac_active_5min":320},{"sum_tx":55719,"sum_pt":1114386,"count_block":13,"max_time":1528542013705,"ac_active_5min":315},{"sum_tx":39313,"sum_pt":786256,"count_block":9,"max_time":1528542033703,"ac_active_5min":298},{"sum_tx":56170,"sum_pt":1123402,"count_block":14,"max_time":1528542037588,"ac_active_5min":306},{"sum_tx":81247,"sum_pt":1624936,"count_block":16,"max_time":1528542043442,"ac_active_5min":312},{"sum_tx":74547,"sum_pt":1490947,"count_block":16,"max_time":1528542047689,"ac_active_5min":328}]