[{"sum_tx":28557,"sum_pt":571146,"count_block":7,"max_time":1528523787650,"ac_active_5min":329},{"sum_tx":72920,"sum_pt":1458403,"count_block":12,"max_time":1528523791728,"ac_active_5min":327},{"sum_tx":53175,"sum_pt":1063492,"count_block":10,"max_time":1528523785759,"ac_active_5min":330},{"sum_tx":51381,"sum_pt":1027624,"count_block":10,"max_time":1528523789441,"ac_active_5min":319},{"sum_tx":84106,"sum_pt":1682126,"count_block":15,"max_time":1528523793567,"ac_active_5min":331},{"sum_tx":63061,"sum_pt":1261213,"count_block":14,"max_time":1528523795594,"ac_active_5min":337},{"sum_tx":44988,"sum_pt":899767,"count_block":10,"max_time":1528523797526,"ac_active_5min":336},{"sum_tx":52359,"sum_pt":1047187,"count_block":8,"max_time":1528523801385,"ac_active_5min":340},{"sum_tx":59195,"sum_pt":1183900,"count_block":12,"max_time":1528523799728,"ac_active_5min":336},{"sum_tx":60680,"sum_pt":1213606,"count_block":11,"max_time":1528523803751,"ac_active_5min":338},{"sum_tx":46829,"sum_pt":936576,"count_block":14,"max_time":1528523807737,"ac_active_5min":345},{"sum_tx":84680,"sum_pt":1693593,"count_block":14,"max_time":1528523811736,"ac_active_5min":343},{"sum_tx":52544,"sum_pt":1050888,"count_block":12,"max_time":1528523819628,"ac_active_5min":337},{"sum_tx":56111,"sum_pt":1122215,"count_block":13,"max_time":1528523805693,"ac_active_5min":343},{"sum_tx":18834,"sum_pt":376671,"count_block":5,"max_time":1528523809565,"ac_active_5min":339},{"sum_tx":47788,"sum_pt":955760,"count_block":9,"max_time":1528523813659,"ac_active_5min":339},{"sum_tx":43108,"sum_pt":862161,"count_block":9,"max_time":1528523815220,"ac_active_5min":334},{"sum_tx":71695,"sum_pt":1433891,"count_block":13,"max_time":1528523817394,"ac_active_5min":336},{"sum_tx":68564,"sum_pt":1371273,"count_block":11,"max_time":1528523821694,"ac_active_5min":339},{"sum_tx":46554,"sum_pt":931075,"count_block":12,"max_time":1528523825733,"ac_active_5min":337},{"sum_tx":43102,"sum_pt":862037,"count_block":12,"max_time":1528523827631,"ac_active_5min":337},{"sum_tx":77338,"sum_pt":1546756,"count_block":16,"max_time":1528523833608,"ac_active_5min":346},{"sum_tx":51351,"sum_pt":1027020,"count_block":7,"max_time":1528523837181,"ac_active_5min":339},{"sum_tx":49012,"sum_pt":980234,"count_block":7,"max_time":1528523841605,"ac_active_5min":338},{"sum_tx":83014,"sum_pt":1660290,"count_block":15,"max_time":1528523823735,"ac_active_5min":344},{"sum_tx":64273,"sum_pt":1285460,"count_block":11,"max_time":1528523829772,"ac_active_5min":336},{"sum_tx":75828,"sum_pt":1516569,"count_block":14,"max_time":1528523831707,"ac_active_5min":344},{"sum_tx":71862,"sum_pt":1437234,"count_block":15,"max_time":1528523835759,"ac_active_5min":351},{"sum_tx":64411,"sum_pt":1288215,"count_block":15,"max_time":1528523839744,"ac_active_5min":339},{"sum_tx":63879,"sum_pt":1277580,"count_block":13,"max_time":1528523843608,"ac_active_5min":341},{"sum_tx":34826,"sum_pt":696519,"count_block":8,"max_time":1528523845633,"ac_active_5min":340},{"sum_tx":44299,"sum_pt":885989,"count_block":7,"max_time":1528523847707,"ac_active_5min":340},{"sum_tx":55200,"sum_pt":1104009,"count_block":11,"max_time":1528523849682,"ac_active_5min":341},{"sum_tx":53844,"sum_pt":1076877,"count_block":11,"max_time":1528523853615,"ac_active_5min":337},{"sum_tx":35339,"sum_pt":706776,"count_block":5,"max_time":1528523855125,"ac_active_5min":328},{"sum_tx":64566,"sum_pt":1291315,"count_block":13,"max_time":1528523857489,"ac_active_5min":330},{"sum_tx":41870,"sum_pt":837402,"count_block":9,"max_time":1528523863603,"ac_active_5min":330},{"sum_tx":63239,"sum_pt":1264774,"count_block":11,"max_time":1528523869530,"ac_active_5min":334},{"sum_tx":26446,"sum_pt":528919,"count_block":8,"max_time":1528523873464,"ac_active_5min":330},{"sum_tx":58347,"sum_pt":1166939,"count_block":11,"max_time":1528523875775,"ac_active_5min":332},{"sum_tx":34222,"sum_pt":684446,"count_block":7,"max_time":1528523879733,"ac_active_5min":321},{"sum_tx":38772,"sum_pt":775438,"count_block":8,"max_time":1528523881367,"ac_active_5min":318},{"sum_tx":57525,"sum_pt":1150503,"count_block":12,"max_time":1528523851773,"ac_active_5min":340},{"sum_tx":51381,"sum_pt":1027612,"count_block":13,"max_time":1528523861686,"ac_active_5min":332},{"sum_tx":40290,"sum_pt":805807,"count_block":9,"max_time":1528523859099,"ac_active_5min":327},{"sum_tx":80695,"sum_pt":1613899,"count_block":16,"max_time":1528523865770,"ac_active_5min":334},{"sum_tx":50863,"sum_pt":1017267,"count_block":9,"max_time":1528523867560,"ac_active_5min":329},{"sum_tx":16955,"sum_pt":0,"count_block":6,"max_time":1528523877501,"ac_active_5min":325},{"sum_tx":57164,"sum_pt":1143275,"count_block":10,"max_time":1528523883603,"ac_active_5min":314},{"sum_tx":24717,"sum_pt":494340,"count_block":5,"max_time":1528523887324,"ac_active_5min":307},{"sum_tx":65697,"sum_pt":1313948,"count_block":11,"max_time":1528523871548,"ac_active_5min":331},{"sum_tx":59897,"sum_pt":1197950,"count_block":12,"max_time":1528523885755,"ac_active_5min":314},{"sum_tx":64015,"sum_pt":1280292,"count_block":13,"max_time":1528523889651,"ac_active_5min":309},{"sum_tx":40159,"sum_pt":803187,"count_block":9,"max_time":1528523893623,"ac_active_5min":298},{"sum_tx":32337,"sum_pt":646737,"count_block":5,"max_time":1528523897056,"ac_active_5min":296},{"sum_tx":73839,"sum_pt":1476777,"count_block":13,"max_time":1528523901350,"ac_active_5min":305},{"sum_tx":25041,"sum_pt":500815,"count_block":9,"max_time":1528523907485,"ac_active_5min":308},{"sum_tx":59702,"sum_pt":1194045,"count_block":9,"max_time":1528523911575,"ac_active_5min":305},{"sum_tx":39455,"sum_pt":789108,"count_block":8,"max_time":1528523915694,"ac_active_5min":308},{"sum_tx":34555,"sum_pt":0,"count_block":11,"max_time":1528523917727,"ac_active_5min":307},{"sum_tx":73126,"sum_pt":1462521,"count_block":13,"max_time":1528523921600,"ac_active_5min":302},{"sum_tx":68830,"sum_pt":1376609,"count_block":11,"max_time":1528523925743,"ac_active_5min":298},{"sum_tx":87581,"sum_pt":1751623,"count_block":13,"max_time":1528523927498,"ac_active_5min":299},{"sum_tx":29309,"sum_pt":586183,"count_block":6,"max_time":1528523931624,"ac_active_5min":298},{"sum_tx":55376,"sum_pt":1107520,"count_block":11,"max_time":1528523939511,"ac_active_5min":310},{"sum_tx":74170,"sum_pt":1483394,"count_block":15,"max_time":1528523943776,"ac_active_5min":314},{"sum_tx":59474,"sum_pt":1189481,"count_block":10,"max_time":1528523891380,"ac_active_5min":304},{"sum_tx":83064,"sum_pt":1661284,"count_block":16,"max_time":1528523895725,"ac_active_5min":299},{"sum_tx":85623,"sum_pt":1712460,"count_block":17,"max_time":1528523899719,"ac_active_5min":300},{"sum_tx":60378,"sum_pt":1207559,"count_block":13,"max_time":1528523903584,"ac_active_5min":305},{"sum_tx":49541,"sum_pt":990828,"count_block":8,"max_time":1528523905753,"ac_active_5min":306},{"sum_tx":58538,"sum_pt":1170754,"count_block":11,"max_time":1528523909761,"ac_active_5min":308},{"sum_tx":61028,"sum_pt":1220566,"count_block":12,"max_time":1528523913688,"ac_active_5min":306},{"sum_tx":14055,"sum_pt":281096,"count_block":4,"max_time":1528523918568,"ac_active_5min":302},{"sum_tx":46495,"sum_pt":929900,"count_block":10,"max_time":1528523923593,"ac_active_5min":303},{"sum_tx":78707,"sum_pt":1574150,"count_block":13,"max_time":1528523929616,"ac_active_5min":302},{"sum_tx":63227,"sum_pt":1264540,"count_block":13,"max_time":1528523935395,"ac_active_5min":303},{"sum_tx":44844,"sum_pt":896890,"count_block":9,"max_time":1528523937535,"ac_active_5min":306},{"sum_tx":45620,"sum_pt":912405,"count_block":8,"max_time":1528523941738,"ac_active_5min":310},{"sum_tx":58878,"sum_pt":1177559,"count_block":11,"max_time":1528523933484,"ac_active_5min":300},{"sum_tx":53109,"sum_pt":1062184,"count_block":10,"max_time":1528523945772,"ac_active_5min":313},{"sum_tx":74145,"sum_pt":1482896,"count_block":11,"max_time":1528523947768,"ac_active_5min":319},{"sum_tx":52040,"sum_pt":1040794,"count_block":13,"max_time":1528523951768,"ac_active_5min":318},{"sum_tx":53747,"sum_pt":1074943,"count_block":11,"max_time":1528523949672,"ac_active_5min":316},{"sum_tx":27940,"sum_pt":558790,"count_block":7,"max_time":1528523953644,"ac_active_5min":317},{"sum_tx":39570,"sum_pt":791395,"count_block":7,"max_time":1528523957602,"ac_active_5min":316},{"sum_tx":63594,"sum_pt":1271881,"count_block":12,"max_time":1528523961735,"ac_active_5min":309},{"sum_tx":62682,"sum_pt":1253639,"count_block":13,"max_time":1528523955456,"ac_active_5min":314},{"sum_tx":53713,"sum_pt":1074253,"count_block":10,"max_time":1528523959731,"ac_active_5min":309},{"sum_tx":56910,"sum_pt":1138194,"count_block":10,"max_time":1528523963554,"ac_active_5min":305},{"sum_tx":47369,"sum_pt":947376,"count_block":9,"max_time":1528523965401,"ac_active_5min":305},{"sum_tx":55665,"sum_pt":1113309,"count_block":10,"max_time":1528523969532,"ac_active_5min":308},{"sum_tx":68803,"sum_pt":1376064,"count_block":11,"max_time":1528523967495,"ac_active_5min":309},{"sum_tx":47870,"sum_pt":957408,"count_block":9,"max_time":1528523970571,"ac_active_5min":308},{"sum_tx":36990,"sum_pt":739798,"count_block":9,"max_time":1528523975424,"ac_active_5min":309},{"sum_tx":58268,"sum_pt":1165362,"count_block":10,"max_time":1528523977526,"ac_active_5min":310},{"sum_tx":52214,"sum_pt":1044279,"count_block":10,"max_time":1528523983753,"ac_active_5min":323},{"sum_tx":38219,"sum_pt":764384,"count_block":11,"max_time":1528523989526,"ac_active_5min":317},{"sum_tx":44103,"sum_pt":882070,"count_block":9,"max_time":1528523993474,"ac_active_5min":322},{"sum_tx":59009,"sum_pt":1180187,"count_block":14,"max_time":1528523995646,"ac_active_5min":322},{"sum_tx":57631,"sum_pt":1152618,"count_block":14,"max_time":1528523999516,"ac_active_5min":327},{"sum_tx":83051,"sum_pt":1661017,"count_block":14,"max_time":1528523973739,"ac_active_5min":310},{"sum_tx":70978,"sum_pt":1419557,"count_block":15,"max_time":1528523981765,"ac_active_5min":324},{"sum_tx":34827,"sum_pt":696530,"count_block":7,"max_time":1528523985662,"ac_active_5min":319},{"sum_tx":72582,"sum_pt":1451635,"count_block":14,"max_time":1528523987511,"ac_active_5min":321},{"sum_tx":52372,"sum_pt":1047447,"count_block":11,"max_time":1528523991773,"ac_active_5min":324},{"sum_tx":84732,"sum_pt":1694638,"count_block":16,"max_time":1528523979381,"ac_active_5min":321},{"sum_tx":47080,"sum_pt":941608,"count_block":11,"max_time":1528523997712,"ac_active_5min":324},{"sum_tx":35189,"sum_pt":703776,"count_block":7,"max_time":1528524001468,"ac_active_5min":326},{"sum_tx":92626,"sum_pt":1852521,"count_block":17,"max_time":1528524005586,"ac_active_5min":326},{"sum_tx":53021,"sum_pt":1060424,"count_block":10,"max_time":1528524009436,"ac_active_5min":325},{"sum_tx":34732,"sum_pt":694641,"count_block":7,"max_time":1528524002930,"ac_active_5min":318},{"sum_tx":47803,"sum_pt":956061,"count_block":11,"max_time":1528524007612,"ac_active_5min":326},{"sum_tx":65091,"sum_pt":1301830,"count_block":12,"max_time":1528524011244,"ac_active_5min":324},{"sum_tx":61827,"sum_pt":1236537,"count_block":11,"max_time":1528524015717,"ac_active_5min":327},{"sum_tx":32826,"sum_pt":656526,"count_block":6,"max_time":1528524017299,"ac_active_5min":326},{"sum_tx":70958,"sum_pt":1419160,"count_block":14,"max_time":1528524021308,"ac_active_5min":328},{"sum_tx":70765,"sum_pt":1415298,"count_block":12,"max_time":1528524013473,"ac_active_5min":329},{"sum_tx":58016,"sum_pt":1160325,"count_block":11,"max_time":1528524019631,"ac_active_5min":327},{"sum_tx":66081,"sum_pt":1321625,"count_block":13,"max_time":1528524027778,"ac_active_5min":340},{"sum_tx":56642,"sum_pt":1132836,"count_block":12,"max_time":1528524031515,"ac_active_5min":343},{"sum_tx":60546,"sum_pt":1210922,"count_block":12,"max_time":1528524023764,"ac_active_5min":328},{"sum_tx":78411,"sum_pt":1568226,"count_block":18,"max_time":1528524025677,"ac_active_5min":339},{"sum_tx":54719,"sum_pt":1094376,"count_block":9,"max_time":1528524029622,"ac_active_5min":340},{"sum_tx":30883,"sum_pt":617664,"count_block":7,"max_time":1528524033300,"ac_active_5min":334},{"sum_tx":50325,"sum_pt":1006493,"count_block":14,"max_time":1528524037703,"ac_active_5min":344},{"sum_tx":49677,"sum_pt":993534,"count_block":8,"max_time":1528524041057,"ac_active_5min":328},{"sum_tx":100609,"sum_pt":2012181,"count_block":15,"max_time":1528524045449,"ac_active_5min":331},{"sum_tx":26895,"sum_pt":0,"count_block":6,"max_time":1528524049742,"ac_active_5min":327},{"sum_tx":57689,"sum_pt":1153770,"count_block":11,"max_time":1528524057669,"ac_active_5min":318},{"sum_tx":67102,"sum_pt":1342037,"count_block":12,"max_time":1528524063248,"ac_active_5min":326},{"sum_tx":38985,"sum_pt":779701,"count_block":8,"max_time":1528524069678,"ac_active_5min":323},{"sum_tx":48983,"sum_pt":979653,"count_block":10,"max_time":1528524073615,"ac_active_5min":320},{"sum_tx":49804,"sum_pt":996079,"count_block":9,"max_time":1528524079312,"ac_active_5min":327},{"sum_tx":65944,"sum_pt":1318883,"count_block":13,"max_time":1528524035714,"ac_active_5min":339},{"sum_tx":33941,"sum_pt":678828,"count_block":7,"max_time":1528524039358,"ac_active_5min":334},{"sum_tx":24856,"sum_pt":497123,"count_block":5,"max_time":1528524043752,"ac_active_5min":323},{"sum_tx":87776,"sum_pt":1755528,"count_block":15,"max_time":1528524047719,"ac_active_5min":331},{"sum_tx":27725,"sum_pt":554502,"count_block":6,"max_time":1528524051396,"ac_active_5min":322},{"sum_tx":38115,"sum_pt":0,"count_block":10,"max_time":1528524053787,"ac_active_5min":324},{"sum_tx":50152,"sum_pt":1003031,"count_block":8,"max_time":1528524055776,"ac_active_5min":318},{"sum_tx":75110,"sum_pt":1502204,"count_block":11,"max_time":1528524059586,"ac_active_5min":315},{"sum_tx":54881,"sum_pt":1097612,"count_block":14,"max_time":1528524061643,"ac_active_5min":322},{"sum_tx":73313,"sum_pt":1466263,"count_block":14,"max_time":1528524065768,"ac_active_5min":323},{"sum_tx":82709,"sum_pt":1654188,"count_block":13,"max_time":1528524067769,"ac_active_5min":325},{"sum_tx":60534,"sum_pt":1210673,"count_block":11,"max_time":1528524071770,"ac_active_5min":321},{"sum_tx":74375,"sum_pt":1487491,"count_block":13,"max_time":1528524075686,"ac_active_5min":322},{"sum_tx":59294,"sum_pt":1185887,"count_block":13,"max_time":1528524077689,"ac_active_5min":329},{"sum_tx":38127,"sum_pt":762541,"count_block":9,"max_time":1528524080958,"ac_active_5min":322},{"sum_tx":47929,"sum_pt":958590,"count_block":13,"max_time":1528524083647,"ac_active_5min":324}]